bytemoji/__init__.py
bytemoji-0.0.4.dist-info/LICENSE.txt
bytemoji-0.0.4.dist-info/METADATA
bytemoji-0.0.4.dist-info/WHEEL
bytemoji-0.0.4.dist-info/top_level.txt
bytemoji-0.0.4.dist-info/RECORD
